QuickRev/__init__.py
QuickRev/main.py
quickrev-0.3.2.dist-info/METADATA
quickrev-0.3.2.dist-info/WHEEL
quickrev-0.3.2.dist-info/licenses/LICENSE
quickrev-0.3.2.dist-info/RECORD
