Metadata-Version: 2.4
Name: QuickRev
Version: 0.3.2
Summary: making a s1mple logical operations
Author-email: Isuagr239 <Za1van@yandex.ru>
License-File: LICENSE
Classifier: License :: OSI Approved :: MIT License
Classifier: Operating System :: OS Independent
Classifier: Programming Language :: Python :: 3
Requires-Python: >=3.10.0
